Metadata-Version: 2.1
Name: oneNeuron-pypi-ShrutiV01
Version: 0.0.2
Summary: Its a description of Perceptron
Home-page: https://github.com/ShrutiV01/oneNeuron_pypi
Author: ShrutiV01
Author-email: shrutiv01@gmail.com
License: UNKNOWN
Project-URL: Bug Tracker, https://github.com/ShrutiV01/oneNeuron_pypi/issues
Platform: UNKNOWN
Classifier: Programming Language :: Python :: 3
Classifier: License :: OSI Approved :: MIT License
Classifier: Operating System :: OS Independent
Requires-Python: >=3.7
License-File: LICENSE
Requires-Dist: numpy
Requires-Dist: tqdm
